CHANGELOG.md
LICENSE
MANIFEST.in
README.rst
TODO.md
setup.cfg
setup.py
tox.ini
flake8_putty/__init__.py
flake8_putty/config.py
flake8_putty/extension.py
flake8_putty.egg-info/PKG-INFO
flake8_putty.egg-info/SOURCES.txt
flake8_putty.egg-info/dependency_links.txt
flake8_putty.egg-info/entry_points.txt
flake8_putty.egg-info/not-zip-safe
flake8_putty.egg-info/requires.txt
flake8_putty.egg-info/top_level.txt
tests/__init__.py
tests/test_config.py
tests/test_integration.py