Metadata-Version: 1.1
Name: flake8-putty
Version: 0.4.0
Summary: Apply a bit of putty to flake8.
Home-page: https://github.com/jayvdb/flake8-putty
Author: John Vandenberg
Author-email: jayvdb@gmail.com
License: MIT
Keywords: flake8 pep8 putty
Platform: UNKNOWN
Classifier: Development Status :: 3 - Alpha
Classifier: Environment :: Console
Classifier: Intended Audience :: Developers
Classifier: License :: OSI Approved :: MIT License
Classifier: Operating System :: OS Independent
Classifier: Programming Language :: Python
Classifier: Programming Language :: Python :: 2
Classifier: Programming Language :: Python :: 3
Classifier: Topic :: Software Development :: Libraries :: Python Modules
Classifier: Topic :: Software Development :: Quality Assurance
